docs/source/conf.py
thetis/__init__.py
thetis/io.py
thetis/mlflow.py
thetis/service.py
thetis-0.2.4.dist-info/licenses/LICENSE.md
thetis-0.2.4.dist-info/METADATA
thetis-0.2.4.dist-info/WHEEL
thetis-0.2.4.dist-info/top_level.txt
thetis-0.2.4.dist-info/RECORD
