Metadata-Version: 2.4
Name: thetis
Version: 0.2.4
Summary: Solution for AI system analysis regarding performance, uncertainty consistency (calibration), fairness, and other aspects relevant for regulatory compliance.
Author: e:fs TechHub GmbH
Author-email: thetis@efs-techhub.com
Maintainer: e:fs TechHub GmbH
Maintainer-email: thetis@efs-techhub.com
License: Proprietary
Project-URL: Homepage, https://thetis.de
Project-URL: Webapp, https://app.thetis.de
Project-URL: GitHub, https://github.com/EFS-OpenSource/Thetis
Project-URL: Documentation, https://efs-opensource.github.io/Thetis
Keywords: ai,safety,security,fairness,robustness,calibration,uncertainty,neural,network,machine,learning,confidence,classification,object,detection,regression,thetis
Classifier: Programming Language :: Python :: 3
Classifier: Operating System :: OS Independent
Classifier: Development Status :: 3 - Alpha
Classifier: Topic :: Scientific/Engineering :: Artificial Intelligence
Requires-Python: >=3.10
License-File: LICENSE.md
Requires-Dist: thetiscore==0.2.4
Dynamic: license-file
